phreeqc/__init__.pyi
phreeqc/__init__.py
phreeqc/_iphreeqc.cpython-311-darwin.so
phreeqc-0.2.1.dist-info/RECORD
phreeqc-0.2.1.dist-info/WHEEL
phreeqc-0.2.1.dist-info/METADATA
phreeqc-0.2.1.dist-info/licenses/LICENSE
phreeqc-0.2.1.dist-info/licenses/NOTICE
