Metadata-Version: 2.1
Name: phreeqc
Version: 0.2.1
Summary: Python bindings for IPHREEQC
Author: Haohan Yang
License: MIT License
Classifier: Development Status :: 4 - Beta
Classifier: License :: OSI Approved :: MIT License
Classifier: Programming Language :: Python :: 3 :: Only
Classifier: Programming Language :: Python :: 3.9
Classifier: Programming Language :: Python :: 3.10
Classifier: Programming Language :: Python :: 3.11
Classifier: Programming Language :: Python :: 3.12
Classifier: Programming Language :: Python :: 3.13
Project-URL: Homepage, https://www.usgs.gov/software/phreeqc-version-3
Project-URL: Repository, https://github.com/haohanyang/phreeqc.git
Project-URL: Issues, https://github.com/haohanyang/phreeqc/issues
Requires-Python: >=3.9
Provides-Extra: test
Requires-Dist: pytest; extra == "test"
